{
    "openapi": "3.0.0",
    "info": {
        "title": "Endpoints do Sys Produtos v1.0",
        "description": "Sys Produtos v1.0",
        "version": "1.0"
    },
    "paths": {
        "/api/categoria/show": {
            "get": {
                "summary": "Show Categoria",
                "description": "Categorias Controller",
                "operationId": "7dce0fa726881bcc2d79d70cad8af87b",
                "responses": {
                    "200": {
                        "description": "OK"
                    }
                }
            }
        },
        "/api/produto/show": {
            "get": {
                "summary": "Exemplo teste",
                "description": "Produtos Controller",
                "operationId": "f2bdf0c48cec12f132f03eeae7c47bd0",
                "responses": {
                    "200": {
                        "description": "OK"
                    }
                }
            }
        }
    }
}